{
    "relaxation": {
        "comment": [],
        "translate": "релаксация, расслабление, отдых, ослабление, развлечение, передышка",
        "transcription": " |ˌriːlækˈseɪʃn|",
        "antonyms": [],
        "mnemonic": [],
        "examples": [
            "I play the piano for relaxation.",
            "What I need is some rest and relaxation.",
            "Meditation allows you to enter a state of deep relaxation.",
            "I like to play the guitar for relaxation.",
            "Sewing is relaxation for some, purgatory for others.",
            "He needs more time off duty for relaxation and rest.",
            "They decided to take a bike tour of the island for recreation and relaxation.",
            "Success keeps her busy. “Relaxation?\" she asks, feigning puzzlement. “What's that?\"",
            "Students need to have time for relaxation and cultural activities, as well as for academic work."
        ],
        "example_translate": [
            "Я играю на фортепиано, чтобы отдохнуть.",
            "Что мне нужно, это немного отдохнуть и расслабиться.",
            "Медитация позволяет войти в состояние глубокого расслабления.",
            "Я люблю играть на гитаре для развлечения.",
            "Для одних шитьё — отдых, для других — сплошное мучение.",
            "Ему нужно больше свободного времени для отдыха и развлечений.",
            "Они решили отправиться на велосипедную экскурсию по острову, чтобы отдохнуть и расслабиться.",
            "Успех не даёт ей сидеть без дела. — Отдых? — с притворным недоумением спрашивает она. — А что это такое?",
            "Студентам необходимо иметь время как для отдыха и культурных мероприятий, так и для научной работы."
        ],
        "synonyms": [],
        "grups": [
            "all_words"
        ]
    }
}