{
  "clever": {
    "comment": [
      "level"
    ],
    "translate": "умный, ловкий, искусный, способный, талантливый, даровитый, юркий, добродушный",
    "transcription": " |ˈklevər|",
    "antonyms": [],
    "mnemonic": [
      "clever [клэ'вэ] умный - Умный (клеве-ту) не слушает.",
      "clever ['klevə]\n***\nУМНЫЙ кот любит клевер. (это) clever\n***\nТы всегда \"ever\", будь умным \"clever\"."
    ],
    "synonyms": [],
    "stars": 1,
    "groups": [
      "e_+_Отк_сл_=_[e]"
    ],
    "examples": [
      {
        "eng": "Don't try to be clever — it doesn't become you.",
        "ru": "Не пытайся умничать — это тебе не идёт.",
        "learn": 0
      },
      {
        "eng": "She's fearfully clever.",
        "ru": "Она ужасно умная.",
        "learn": 0
      },
      {
        "eng": "However he did it, it was very clever.",
        "ru": "Не знаю, как он это сделал, но это было очень умно.",
        "learn": 0
      },
      {
        "eng": "It's a clever plan, but will it get by?",
        "ru": "Это остроумный план, но удастся ли его провернуть?",
        "learn": 0
      },
      {
        "eng": "She interjected clever remarks",
        "ru": "Она сделала разумные замечания.",
        "learn": 0
      },
      {
        "eng": "Some cats are clever enough to figure out how to operate doorknobs.",
        "ru": "Некоторым кошкам хватает ума сообразить, как обращаться с дверными ручками.",
        "learn": 0
      },
      {
        "eng": "Bill's very clever with his hands.",
        "ru": "У Билла очень умелые руки.",
        "learn": 0
      },
      {
        "eng": "Nobody disputed that Davey was clever.",
        "ru": "Никто не подвергал сомнению тот факт, что Деви умён.",
        "learn": 0
      },
      {
        "eng": "What a clever little gadget!",
        "ru": "Какая толковая безделушка!",
        "learn": 0
      },
      {
        "eng": "The painting was a very clever forgery.",
        "ru": "Эта картина была очень умелой подделкой.",
        "learn": 0
      },
      {
        "eng": "He is fairly clever with computers.",
        "ru": "Он довольно хорошо разбирается в компьютерах.",
        "learn": 0
      },
      {
        "eng": "That's the cleverest idea I've heard yet!",
        "ru": "Это самая умная мысль, которую мне когда-либо приходилось слышать!",
        "learn": 0
      },
      {
        "eng": "She invented a clever excuse.",
        "ru": "Она выдумала хитрую отговорку.",
        "learn": 1
      },
      {
        "eng": "He was clever at finding bargains.",
        "ru": "Он умел находить выгодные предложения.",
        "learn": 0
      },
      {
        "eng": "You fell for my clever snare, you fool!",
        "ru": "Ты попался на мою хитрую уловку, глупец!",
        "learn": 0
      },
      {
        "eng": "The clever salesman cheated the old lady into giving him all her money.",
        "ru": "Хитрый продавец вытянул из старухи все деньги.",
        "learn": 0
      },
      {
        "eng": "Lewis was moody and brilliantly clever.",
        "ru": "Льюис был капризным и обладал блестящим умом.",
        "learn": 0
      },
      {
        "eng": "a writer known for her clever use of irony",
        "ru": "писательница, известная умелым использованием иронии",
        "learn": 0
      },
      {
        "eng": "I suppose you thought you were being clever!",
        "ru": "Наверное, ты считал себя очень умным!",
        "learn": 0
      },
      {
        "eng": "Lucy is quite clever and does well at school.",
        "ru": "Люси довольно умная, и хорошо успевает в школе.",
        "learn": 0
      },
      {
        "eng": "She found a clever hiding place for the letter.",
        "ru": "Она нашла хитрый тайник для письма.",
        "learn": 0
      },
      {
        "eng": "She was always very clever at getting around the rules.",
        "ru": "Она всегда очень талантливо обходила правила.",
        "learn": 0
      },
      {
        "eng": "These clever students lap up all the information that I can give them.",
        "ru": "Эти умные ребята впитывают всю информацию, которую я могу им дать.",
        "learn": 0
      },
      {
        "eng": "a house with many clever little flourishes",
        "ru": "дом со множеством мелких изящных завитушек",
        "learn": 0
      },
      {
        "eng": "The ancient Egyptians were a clever bunch.",
        "ru": "Древние Египтяне были людьми смышлёными.",
        "learn": 0
      },
      {
        "eng": "It was a film noir with some clever twists.",
        "ru": "Это был фильм-нуар с несколькими хитрыми поворотами сюжета.",
        "learn": 0
      },
      {
        "eng": "The best part of the book is the clever dialogue.",
        "ru": "Лучшая часть этой книги — умные диалоги.",
        "learn": 0
      },
      {
        "eng": "A clever lawyer can cozen the judge into agreement.",
        "ru": "Ловкий адвокат сумеет так заморочить судье голову, что тот согласится с ним во всем.",
        "learn": 0
      },
      {
        "eng": "Whosesoever be the speech, it was full of clever ideas.",
        "ru": "Кому бы ни принадлежала эта речь, в ней было много умных мыслей.",
        "learn": 0
      },
      {
        "eng": "A clever move on our part rolled up the enemy's weak side.",
        "ru": "Искусный манёвр с нашей стороны смял вражеский фланг.",
        "learn": 0
      }
    ]
  }
}