{
  "frankly": {
    "comment": [
      "franchise",
      "frantic",
      "rank",
      "frank"
    ],
    "translate": "откровенно, прямо",
    "transcription": " |ˈfræŋkli|",
    "antonyms": [],
    "mnemonic": [
      "frank [fræŋk]\nfrankly ['fræŋkli] - откровенно\n***\nИСКРЕННИЙ всегда даст франк. (это) frank\nОткровенный, открытый. Франкировать.\n***\nТы был откровенный \"frank\"\nи рассказал, что ты выпил \"drank\"."
    ],
    "synonyms": [],
    "stars": 1,
    "groups": [],
    "examples": [
      {
        "eng": "You can speak frankly to us.",
        "ru": "С нами можно говорить откровенно.",
        "learn": 1
      },
      {
        "eng": "Frankly, I think the Internet is overrated.",
        "ru": "Откровенно говоря, я считаю, что значение Интернета переоценено.",
        "learn": 0
      },
      {
        "eng": "Frankly, my dear, I don't give a damn.",
        "ru": "Откровенно говоря, моя дорогая, мне наплевать.",
        "learn": 0
      },
      {
        "eng": "She answered all our questions frankly.",
        "ru": "Она откровенно ответила на все наши вопросы.",
        "learn": 1
      },
      {
        "eng": "Frankly, I'd rather stay at home than go to the movies tonight.",
        "ru": "Честно говоря, я предпочёл бы сегодня вечером остаться дома, чем идти в кино.",
        "learn": 1
      },
      {
        "eng": "Nicholas frankly admitted that the report was a pack of lies.",
        "ru": "Никлас откровенно признался, что в отчёте не было ничего, кроме вранья.",
        "learn": 0
      },
      {
        "eng": "Mme. Sarah Bernhardt frankly says she sees nothing wrong in the altogether.",
        "ru": "Мадам Сара Бернар честно призналась, что не видит ничего плохого в обнаженных моделях.",
        "learn": 0
      },
      {
        "eng": "He took off his politician's hat and talked frankly.",
        "ru": "Он сбросил с себя маску политика и заговорил искренне.",
        "learn": 0
      },
      {
        "eng": "Frankly, it's an undesirable and unpleasant job.",
        "ru": "Откровенно говоря, это работа дрянная и неприятная.",
        "learn": 0
      },
      {
        "eng": "Frankly, I wouldn't trust his emotional state right now.",
        "ru": "Если честно, сейчас я бы не стал доверять его эмоциональному состоянию.",
        "learn": 1
      }
    ]
  }
}