{
    "indictment": {
        "comment": [],
        "translate": "обвинительный акт, обвинение, акт, предъявление обвинения",
        "transcription": " |ɪnˈdaɪtmənt|",
        "antonyms": [],
        "mnemonic": [],
        "examples": [
            "The book is an indictment of modern philosophy.",
            "No one was surprised by her indictment.",
            "The fact that these children cannot read is a damning indictment of our education system.",
            "She intended the film to be an indictment of the media."
        ],
        "example_translate": [
            "Данная книга является обвинением в адрес современной философии.",
            "Никто не был удивлен обвинениям выдвинутым против неё.",
            "Тот факт, что эти дети не могут читать, является убийственным обвинением в адрес нашей системы образования.",
            "Она хотела, чтобы этот фильм стал обличением СМИ."
        ],
        "synonyms": [],
        "grups": [
            "all_words"
        ],
        "stars": 0
    }
}