{
  "liberate": {
    "comment": [],
    "translate": "освобождать, высвобождать, выделять, раскрепощать, воровать",
    "transcription": " |ˈlɪbəreɪt|",
    "antonyms": [],
    "mnemonic": [],
    "synonyms": [],
    "groups": [],
    "stars": 0,
    "examples": [
      {
        "eng": "Rebels fought to liberate the country.",
        "ru": "Повстанцы боролись за освобождение страны.",
        "learn": 0
      },
      {
        "eng": "A few days later, our armies liberated the city.",
        "ru": "Несколько дней спустя наши войска освободили город.",
        "learn": 0
      },
      {
        "eng": "A war was fought in the United States in the 19th century to liberate black people from slavery.",
        "ru": "В 19-м веке в США шла война за освобождение негров от рабства.",
        "learn": 0
      },
      {
        "eng": "He was using materials that he had liberated from a construction site.",
        "ru": "Он использовал материалы, которые спёр со стройплощадки.",
        "learn": 0
      },
      {
        "eng": "The students liberated their slaves upon graduating from the university.",
        "ru": "Студенты освободили своих рабов после окончания университета.",
        "learn": 0
      },
      {
        "eng": "Laptop computers could liberate workers from their desks.",
        "ru": "Портативные компьютеры могли бы освободить работников от необходимости находится на рабочих местах.",
        "learn": 0
      }
    ]
  }
}