{
  "lower": {
    "comment": [
      "tower",
      "owe",
      "vowel",
      "towel"
    ],
    "translate": "нижний, низкий, ниже, понизить, снижаться, хмурый вид",
    "transcription": " |ˈloʊər|",
    "antonyms": [],
    "mnemonic": [],
    "synonyms": [],
    "stars": 2,
    "groups": [],
    "examples": [
      {
        "eng": "Do you think we should lower the price?",
        "ru": "Думаешь, нам следует снизить цену?",
        "learn": 1
      },
      {
        "eng": "She bit her lower lip.",
        "ru": "Она прикусила нижнюю губу.",
        "learn": 0
      },
      {
        "eng": "Don't lower yourself, don't be the way they are.",
        "ru": "Не унижайся, не будь таким, как они.",
        "learn": 0
      },
      {
        "eng": "I tweaked my lower back.",
        "ru": "Я потянул поясницу.",
        "learn": 0
      },
      {
        "eng": "I felt a sharp pain in my lower back.",
        "ru": "Я почувствовал острую боль в нижней части спины.",
        "learn": 0
      },
      {
        "eng": "Lower empire",
        "ru": "Восточная Римская империя, Византия",
        "learn": 0
      },
      {
        "eng": "We settled for a lower price.",
        "ru": "Мы согласились на более низкую цену.",
        "learn": 1
      },
      {
        "eng": "It is thus that mediocre people seek to lower great men.",
        "ru": "Это верно, что заурядные люди стараются принизить великих.",
        "learn": 0
      },
      {
        "eng": "the ship's upper and lower decks",
        "ru": "верхняя и нижняя палубы судна",
        "learn": 0
      },
      {
        "eng": "Nina chewed her lower lip anxiously.",
        "ru": "Из-за тревоги Нина кусала свою нижнюю губу.",
        "learn": 0
      },
      {
        "eng": "The lower meadow is absolutely flat.",
        "ru": "Нижняя часть луга абсолютно ровная.",
        "learn": 0
      },
      {
        "eng": "Can the government be prevailed upon to lower taxes?",
        "ru": "Можно ли убедить правительство снизить налоги?",
        "learn": 0
      },
      {
        "eng": "Two reporters had to help lower the coffin into the grave.",
        "ru": "Двум репортёрам пришлось помочь опустить гроб в могилу.",
        "learn": 1
      },
      {
        "eng": "The lower part of his face was all shot away.",
        "ru": "Нижняя часть его лица была обезображена выстрелом.",
        "learn": 0
      },
      {
        "eng": "We brought the dealer down to a much lower figure.",
        "ru": "Мы насели на продавца, и он довольно заметно сбросил цену.",
        "learn": 0
      },
      {
        "eng": "His lower jaw protrudes slightly.",
        "ru": "Его нижняя челюсть слегка выступает вперёд.",
        "learn": 0
      },
      {
        "eng": "She suffers with pain in her lower back.",
        "ru": "Она страдает от болей в пояснице.",
        "learn": 0
      },
      {
        "eng": "They have bricked up the lower part of the window.",
        "ru": "Они выложили кирпичом нижнюю часть окна.",
        "learn": 0
      },
      {
        "eng": "The airplane will descend to a lower altitude soon.",
        "ru": "Самолёт вскоре опустится на меньшую высоту.",
        "learn": 1
      },
      {
        "eng": "The new law will lower income taxes for most taxpayers.",
        "ru": "Новый закон позволит снизить налог на прибыль для большинства налогоплательщиков.",
        "learn": 0
      },
      {
        "eng": "In practice women receive much lower wages than their male colleagues.",
        "ru": "На практике, женщины получают гораздо меньшую зарплату, чем их коллеги-мужчины.",
        "learn": 0
      },
      {
        "eng": "Sing those bars an octave lower.",
        "ru": "Спойте эти такты октавой ниже.",
        "learn": 0
      },
      {
        "eng": "She has a pain in the lower back region.",
        "ru": "У неё боли в области поясницы.",
        "learn": 0
      },
      {
        "eng": "A bass voice is lower than a baritone voice.",
        "ru": "Бас — более низкий голос, чем баритон.",
        "learn": 1
      },
      {
        "eng": "Lower interest rates have weakened the dollar.",
        "ru": "Более низкие процентные ставки привели к ослаблению доллара.",
        "learn": 0
      },
      {
        "eng": "The lower branches of the bush began to rot off.",
        "ru": "Нижние ветви куста начали гнить и отмирать.",
        "learn": 0
      },
      {
        "eng": "Lower interest rates should spur economic growth.",
        "ru": "Более низкие процентные ставки должны стимулировать экономический рост.",
        "learn": 0
      },
      {
        "eng": "The lower tier has 10,000 seats.",
        "ru": "На нижнем ярусе — десять тысяч мест.",
        "learn": 0
      },
      {
        "eng": "The lower back forms a concavity.",
        "ru": "Нижняя часть спины образует вогнутость.",
        "learn": 0
      },
      {
        "eng": "We applaud the decision to lower taxes.",
        "ru": "Мы приветствуем решение понизить налоги.",
        "learn": 0
      }
    ]
  }
}