{
  "dissatisfied": {
    "comment": [
      "satisfy",
      "satisfaction",
      "satisfactory",
      "satisfied",
      "satisfying"
    ],
    "translate": "недовольный, неудовлетворенный, раздосадованный",
    "transcription": " |dɪsˈsætɪsfaɪd|",
    "antonyms": [],
    "mnemonic": [],
    "synonyms": [],
    "stars": 1,
    "groups": [],
    "examples": [
      {
        "eng": "She was dissatisfied by the poor service.",
        "ru": "Она была недовольна плохим обслуживанием",
        "learn": 1
      },
      {
        "eng": "I had no reason to be dissatisfied with my success.",
        "ru": "У меня не было причин быть недовольным моим успехом.",
        "learn": 1
      },
      {
        "eng": "He was dissatisfied with his neutral life.",
        "ru": "Он был недоволен своей тусклой жизнью.",
        "learn": 0
      },
      {
        "eng": "Many people are dissatisfied at / with not finding suitable jobs.",
        "ru": "Многие люди не удовлетворены тем, что не могут найти подходящую работу.",
        "learn": 1
      },
      {
        "eng": "Research indicates that over 81% of teachers are dissatisfied with their salary.",
        "ru": "Исследования показывают, что более 81% преподавателей недовольны своей заработной платой.",
        "learn": 1
      }
    ]
  }
}