{
    "distributor": {
        "comment": [
            "district",
            "distribute",
            "distribution",
            "distributed"
        ],
        "translate": "распределитель, распределитель зажигания, агент по продаже, гудронатор",
        "transcription": " |dɪˈstrɪbjətər|",
        "antonyms": [],
        "mnemonic": [],
        "examples": [
            "His company is a large distributor of software products."
        ],
        "example_translate": [
            "Его компания является крупным дистрибьютором программных продуктов."
        ],
        "synonyms": [],
        "grups": [
            "all_words"
        ]
    }
}